Metadata-Version: 2.1
Name: set-django-env
Version: 1.0
Summary: 安全性
Home-page: https://github.com/
Author: liyubin
Author-email: 1399393088@qq.com
License: MIT Licence
Keywords: pip,set_django_env,featureextraction
Platform: any
